setup.py
vcore_api/__init__.py
vcore_api/collections.py
vcore_api/utils.py
vcore_api.egg-info/PKG-INFO
vcore_api.egg-info/SOURCES.txt
vcore_api.egg-info/dependency_links.txt
vcore_api.egg-info/requires.txt
vcore_api.egg-info/top_level.txt
vcore_api/assets/__init__.py
vcore_api/assets/base_asset.py
vcore_api/assets/docker/__init__.py
vcore_api/assets/docker/containers.py
vcore_api/assets/docker/docker_asset_collector.py
vcore_api/assets/docker/images.py
vcore_api/base/__init__.py
vcore_api/base/io.py
vcore_api/core/__init__.py
vcore_api/core/api.py
vcore_api/core/exceptions.py
vcore_api/core/reqeust_handler.py
vcore_api/core/response.py